pubsub_library/__init__.py
pubsub_library/main.py
pubsub_library/interfaces/__init__.py
pubsub_library/interfaces/pubsub.py
pubsub_library/repositories/__init__.py
pubsub_library/repositories/rabbitmq.py
pubsub_library/repositories/redis.py
pubsub_library/repositories/service_bus.py
pubsub_library-0.3.0.dist-info/METADATA
pubsub_library-0.3.0.dist-info/WHEEL
pubsub_library-0.3.0.dist-info/top_level.txt
pubsub_library-0.3.0.dist-info/RECORD
